yamlchecker/__init__.py
yamlchecker/yamlchecker.py
yamlchecker-0.1.11.dist-info/METADATA
yamlchecker-0.1.11.dist-info/WHEEL
yamlchecker-0.1.11.dist-info/entry_points.txt
yamlchecker-0.1.11.dist-info/top_level.txt
yamlchecker-0.1.11.dist-info/RECORD
