Metadata-Version: 2.1
Name: yamlchecker
Version: 0.1.11
Summary: Checker for YAML test cases files
Home-page: UNKNOWN
Author: kodSIM
Author-email: UNKNOWN
License: UNKNOWN
Platform: UNKNOWN
Requires-Dist: Click
Requires-Dist: Markdown
Requires-Dist: PyYAML
Requires-Dist: yamllint
